truss_transfer/__init__.py
truss_transfer/truss_transfer.abi3.so
truss_transfer-0.0.39.dist-info/METADATA
truss_transfer-0.0.39.dist-info/WHEEL
truss_transfer-0.0.39.dist-info/RECORD
