Metadata-Version: 2.4
Name: truss_transfer
Version: 0.0.39
Classifier: Programming Language :: Rust
Classifier: Programming Language :: Python :: Implementation :: CPython
Classifier: Programming Language :: Python :: Implementation :: PyPy
Summary: Speed up file transfers with the baseten.co + baseten_fs.
Author-email: Michael Feil <no-reply@baseten.co>
License-Expression: MIT
Requires-Python: >=3.8
Project-URL: Issues, https://github.com/basetenlabs/truss/issues
Project-URL: Repository, https://github.com/basetenlabs/truss.git
